nxrm_sdk/__init__.py
nxrm_sdk/api/__init__.py
nxrm_sdk/api/assets_api.py
nxrm_sdk/api/azure_blob_store_api.py
nxrm_sdk/api/blob_store_api.py
nxrm_sdk/api/components_api.py
nxrm_sdk/api/content_selectors_api.py
nxrm_sdk/api/email_api.py
nxrm_sdk/api/formats_api.py
nxrm_sdk/api/lifecycle_api.py
nxrm_sdk/api/manage_iq_server_configuration_api.py
nxrm_sdk/api/product_licensing_api.py
nxrm_sdk/api/read_only_api.py
nxrm_sdk/api/replication_api.py
nxrm_sdk/api/repository_management_api.py
nxrm_sdk/api/routing_rules_api.py
nxrm_sdk/api/script_api.py
nxrm_sdk/api/search_api.py
nxrm_sdk/api/security_atlassian_crowd_api.py
nxrm_sdk/api/security_certificates_api.py
nxrm_sdk/api/security_management_anonymous_access_api.py
nxrm_sdk/api/security_management_api.py
nxrm_sdk/api/security_management_jwt_api.py
nxrm_sdk/api/security_management_ldap_api.py
nxrm_sdk/api/security_management_privileges_api.py
nxrm_sdk/api/security_management_realms_api.py
nxrm_sdk/api/security_management_roles_api.py
nxrm_sdk/api/security_management_saml_api.py
nxrm_sdk/api/security_management_user_tokens_api.py
nxrm_sdk/api/security_management_users_api.py
nxrm_sdk/api/staging_api.py
nxrm_sdk/api/status_api.py
nxrm_sdk/api/support_api.py
nxrm_sdk/api/tags_api.py
nxrm_sdk/api/tasks_api.py
nxrm_sdk/api_client.py
nxrm_sdk/configuration.py
nxrm_sdk/models/__init__.py
nxrm_sdk/models/abstract_api_repository.py
nxrm_sdk/models/anonymous_access_settings_xo.py
nxrm_sdk/models/api_certificate.py
nxrm_sdk/models/api_create_user.py
nxrm_sdk/models/api_email_configuration.py
nxrm_sdk/models/api_email_validation.py
nxrm_sdk/models/api_license_details_xo.py
nxrm_sdk/models/api_privilege.py
nxrm_sdk/models/api_privilege_application_request.py
nxrm_sdk/models/api_privilege_repository_admin_request.py
nxrm_sdk/models/api_privilege_repository_content_selector_request.py
nxrm_sdk/models/api_privilege_repository_view_request.py
nxrm_sdk/models/api_privilege_script_request.py
nxrm_sdk/models/api_privilege_wildcard_request.py
sonatype_nxrm_sdk-0.1.5.dist-info/LICENSE
sonatype_nxrm_sdk-0.1.5.dist-info/METADATA
sonatype_nxrm_sdk-0.1.5.dist-info/WHEEL
sonatype_nxrm_sdk-0.1.5.dist-info/RECORD
